pyverdict/__init__.py
pyverdict/metadata.json
pyverdict/verdictcommon.py
pyverdict/verdictcontext.py
pyverdict/verdictexception.py
pyverdict/verdictresult.py
pyverdict/datatype_converters/__init__.py
pyverdict/datatype_converters/converter_base.py
pyverdict/datatype_converters/impala_converter.py
pyverdict/datatype_converters/mysql_converter.py
pyverdict/datatype_converters/postgres_converter.py
pyverdict/datatype_converters/presto_converter.py
pyverdict/datatype_converters/redshift_converter.py
pyverdict/lib/ImpalaJDBC41-2.6.3.jar
pyverdict/lib/RedshiftJDBC41-1.2.16.1027.jar
pyverdict/lib/mysql-connector-java-5.1.46.jar
pyverdict/lib/postgresql-42.2.5.jre7.jar
pyverdict/lib/presto-jdbc-0.213.jar
pyverdict/verdict_jar/verdictdb-core-0.5.9-jar-with-dependencies.jar
tests/__init__.py
tests/test_impala_datatypes.py
tests/test_impala_simple_queries.py
tests/test_mysql_datatypes.py
tests/test_mysql_simple_queries.py
tests/test_postgres_datatypes.py
tests/test_postgres_simple_queries.py
tests/test_presto_datatypes.py
tests/test_presto_simple_queries.py
tests/test_redshift_datatypes.py
tests/test_redshift_simple_queries.py
tests/test_verdictcontext.py
pyverdict-0.1.3.2.dist-info/LICENSE
pyverdict-0.1.3.2.dist-info/METADATA
pyverdict-0.1.3.2.dist-info/WHEEL
pyverdict-0.1.3.2.dist-info/top_level.txt
pyverdict-0.1.3.2.dist-info/RECORD
