Metadata-Version: 2.1
Name: pyverdict
Version: 0.1.3.2
Summary: Python interface for VerdictDB
Home-page: http://verdictdb.org
Author: Barzan Mozafari, Yongjoo Park
Author-email: mozafari@umich.edu, pyongjoo@umich.edu
License: Apache License, Version 2.0
Platform: UNKNOWN
Requires-Dist: py4j (>=0.10.7)
Requires-Dist: numpy (>=1.9)
Requires-Dist: pandas (>=0.23)
Requires-Dist: python-dateutil (>=2.7.5)
